semantic_cache/__init__.py
semantic_cache-0.1.1.dist-info/METADATA
semantic_cache-0.1.1.dist-info/WHEEL
semantic_cache-0.1.1.dist-info/licenses/LICENSE
semantic_cache-0.1.1.dist-info/RECORD
