Metadata-Version: 2.3
Name: semantic-cache
Version: 0.1.1
Summary: Semantic Caching on python functions
Author-email: Rajaniraiyn R <rajaniraiyn@gmail.com>
License-File: LICENSE
Requires-Python: >=3.8
Requires-Dist: qdrant-client[fastembed]>=1.8.2
